CHANGELOG.txt
LICENSE.txt
MANIFEST.in
README.txt
setup.py
zeroone_ai/__init__.py
zeroone_ai.egg-info/PKG-INFO
zeroone_ai.egg-info/SOURCES.txt
zeroone_ai.egg-info/dependency_links.txt
zeroone_ai.egg-info/requires.txt
zeroone_ai.egg-info/top_level.txt