Metadata-Version: 2.1
Name: zeroone-ai
Version: 0.0.11
Summary: With this package you can make an simple AI that can predict a zero or a one.
Home-page: https://github.com/MathijsTak/ZeroOneAi
Author: MathijsTak
Author-email: mathijs.tak@outlook.com
License: MIT
Keywords: zeroone zero one ai zerooneai zeroai oneai zeroone-ai
Platform: UNKNOWN
Classifier: Development Status :: 5 - Production/Stable
Classifier: Intended Audience :: Education
Classifier: Operating System :: Microsoft :: Windows :: Windows 10
Classifier: License :: OSI Approved :: MIT License
Classifier: Programming Language :: Python :: 3
License-File: LICENSE.txt
